ampo/__init__.py
ampo/db.py
ampo/errors.py
ampo/log.py
ampo/types.py
ampo/utils.py
ampo/worker.py
ampo-0.7.0.dist-info/METADATA
ampo-0.7.0.dist-info/WHEEL
ampo-0.7.0.dist-info/RECORD
