Metadata-Version: 2.4
Name: ampo
Version: 0.7.0
Summary: Python library async ORM for mongodb. Object as pyDantic
Project-URL: Homepage, https://github.com/shizacat/ampo
Author: Alexey Matveev
Classifier: License :: OSI Approved :: MIT License
Classifier: Operating System :: OS Independent
Classifier: Programming Language :: Python :: 3
Classifier: Programming Language :: Python :: 3.8
Classifier: Topic :: Software Development :: Libraries :: Python Modules
Requires-Python: >=3.8
Requires-Dist: motor>=3.2
Requires-Dist: pydantic>=2.8
